Metadata-Version: 2.1
Name: cosmicexcelchecker
Version: 0.2.3
Summary: A high flexibility package for checking cosmic-related excels under CMDI cosmic standards
Author: TimG233
Author-email: gaosh0830@gmail.com
Maintainer: TimG233
License: GPL-3.0-only
Keywords: cosmic,excel,CMDI,checker,data
Platform: any
Classifier: License :: OSI Approved :: GNU General Public License v3 (GPLv3)
Classifier: Programming Language :: Python :: 3.9
Classifier: Programming Language :: Python :: 3.10
Requires-Python: >=3.9
